{
  "content": "# Express Checkout Element comparison\n\n## Compare the features for the Express Checkout Element and the Payment Request Button.\n\nLike the [Payment Request\nButton](https://docs.stripe.com/stripe-js/elements/payment-request-button), you\ncan use the [Express Checkout\nElement](https://docs.stripe.com/elements/express-checkout-element) to accept\ncard or [wallet](https://docs.stripe.com/payments/wallets) payments through one\nor more payment buttons. While both Elements support common payment flows, the\nExpress Checkout Element provides instant access to additional payment methods.\n\nIf you currently use the Payment Request Button, you can\n[migrate](https://docs.stripe.com/elements/express-checkout-element/migration)\nto the Express Checkout Element.\n\nFeaturesExpress Checkout Element Payment Request Button Accept all\nStripe-supported [card\nbrands](https://docs.stripe.com/payments/cards#supported-card-brands) through\nwallet pay buttonsAccept payments with other payment methodsEnable faster\ncheckout with [Link](https://docs.stripe.com/payments/link)Enable using\ndifferent [funding\nsources](https://docs.stripe.com/payments/link/add-link-elements-integration#multiple-funding-sources)\nwith LinkSupport Apple Pay [merchant\ntokens](https://developer.apple.com/apple-pay/merchant-tokens/)Display multiple\nbuttons (such as Apple Pay and Google Pay) at the same timeChange the button\nappearance and themeHandle [3D\nSecure](https://docs.stripe.com/payments/3d-secure) authentication\n## See also\n\n- [Migrate to the Express Checkout\nElement](https://docs.stripe.com/elements/express-checkout-element/migration)\n\n## Links\n\n- [Payment Request\nButton](https://docs.stripe.com/stripe-js/elements/payment-request-button)\n- [Express Checkout\nElement](https://docs.stripe.com/elements/express-checkout-element)\n- [wallet](https://docs.stripe.com/payments/wallets)\n- [migrate](https://docs.stripe.com/elements/express-checkout-element/migration)\n- [card brands](https://docs.stripe.com/payments/cards#supported-card-brands)\n- [Link](https://docs.stripe.com/payments/link)\n- [funding\nsources](https://docs.stripe.com/payments/link/add-link-elements-integration#multiple-funding-sources)\n- [merchant tokens](https://developer.apple.com/apple-pay/merchant-tokens/)\n- [3D Secure](https://docs.stripe.com/payments/3d-secure)",
  "metadata": {
    "title": "Express Checkout Element comparison | Stripe Documentation",
    "description": "Compare the features for the Express Checkout Element and the Payment Request Button.",
    "sourceURL": "https://docs.stripe.com/elements/express-checkout-element/comparison"
  }
}