{
  "content": "# Audit your numbers\n\n## Use the Stripe Dashboard to examine the details of your revenue numbers.\n\nYou can get a detailed view of accounting numbers from the Dashboard either by\ncustomers or by transactions for:\n\n- Each number in the [monthly summary\nreport](https://docs.stripe.com/revenue-recognition/reports/monthly-summary)\n- Each number in the [revenue waterfall\nreport](https://docs.stripe.com/revenue-recognition/reports/waterfall)\n- Each number in the AR aging summary report\n- A customer\n- An invoice\n- An invoice line item\n- A payment\n- An Apple subscriber\n- A Google order\n\n## Monthly summary report\n\nChoose a month in [the monthly summary\nsection](https://dashboard.stripe.com/revenue-recognition) to get a report of\nthe activity that occurred during that time.\n\nClick an amount in the report to see the details of this number broken down into\na list of customers and their total amount for the month.\n\nIn the customer list, click a customer name to see all their transactions for\nthe month.\n\n## Revenue waterfall report\n\nSelect a range of dates in [the waterfall\nsection](https://dashboard.stripe.com/revenue-recognition/accounting-reports)\n(by month-year) to see the distribution of revenue across one or more accounting\nperiods.\n\nClick an amount in the report to see the details of this number broken down into\na list of customers and their total.\n\nIn the customer list, click a customer name to see all their transactions for\nthe specified dates.\n\n## AR aging summary report\n\nSpecify a time period in [the AR aging summary\nsection](https://dashboard.stripe.com/revenue-recognition) to see unpaid invoice\nbalances along with the length of time the invoices have been outstanding (age).\n\nClick an amount in the table to see the details of this number broken down into\na list of customers or invoices. From the customer list, select a customer to\nsee all their invoices for the specified time period and age. From the invoice\nlist, select an invoice to see its invoice details.\n\n## Audit numbers for a customer\n\nTo view account balances for a customer:\n\n- Select a customer from the [Customers\nview](https://dashboard.stripe.com/customers) in the Dashboard.\n- In the **Invoices** section, click **View revenue recognition** to see the\ncustomer’s accounting details, which include:\n- The total balance for each account\n- The details on each account across the accounting periods\n\n## Audit numbers for an invoice\n\nTo view account balances for an invoice:\n\n- Select an invoice from the [Invoices\nview](https://dashboard.stripe.com/invoices) in the Dashboard.\n- Click the overflow menu () > **View revenue recognition** to see the invoice’s\naccounting details, which include:\n- The total balance for each account\n- The details on each account across the accounting periods\n\n## Audit numbers for an invoice line item\n\nTo view account balances for an invoice line item:\n\n- Select an invoice from the [Invoices\nview](https://dashboard.stripe.com/invoices) in the Dashboard.\n- In the **Summary** section, click the overflow menu () next to the line item >\n**View revenue recognition** to see the line item’s accounting details, which\ninclude:\n- The total balance for each account\n- The details on each account across the accounting periods\n\n## Audit numbers for a payment\n\nTo view account balances for a payment:\n\n- Select a payment from the [Payments\nview](https://dashboard.stripe.com/payments) in the Dashboard.\n- In the **Payment breakdown** section, click the overflow menu () > **View\nrevenue recognition** to see the payment’s accounting details, which include:\n- The total balance for each account\n- The details on each account across the accounting periods\n\n## Audit numbers for an Apple subscriber\n\nView Apple subscribers as customers in the [Monthly\nsummary](https://docs.stripe.com/revenue-recognition/reports/monthly-summary)\nsection in the Customer tab. For detailed steps, see [Stripe Connector for the\nApple App Store\npage](https://docs.stripe.com/revenue-recognition/data-import/apple-app-store#audit-numbers).\n\n## Audit numbers for a Google order\n\nView Google orders as invoices starting from the [Monthly\nsummary](https://docs.stripe.com/revenue-recognition/reports/monthly-summary)\nsection in the Invoice tab. For detailed steps, visit the [Stripe Connector for\nGoogle Play\npage](https://docs.stripe.com/revenue-recognition/data-import/google-play#audit-numbers).\n\n## Links\n\n- [monthly summary\nreport](https://docs.stripe.com/revenue-recognition/reports/monthly-summary)\n- [revenue waterfall\nreport](https://docs.stripe.com/revenue-recognition/reports/waterfall)\n- [the monthly summary\nsection](https://dashboard.stripe.com/revenue-recognition)\n- [the waterfall\nsection](https://dashboard.stripe.com/revenue-recognition/accounting-reports)\n- [Customers view](https://dashboard.stripe.com/customers)\n- [Invoices view](https://dashboard.stripe.com/invoices)\n- [Payments view](https://dashboard.stripe.com/payments)\n- [Stripe Connector for the Apple App Store\npage](https://docs.stripe.com/revenue-recognition/data-import/apple-app-store#audit-numbers)\n- [Stripe Connector for Google Play\npage](https://docs.stripe.com/revenue-recognition/data-import/google-play#audit-numbers)",
  "metadata": {
    "title": "Audit your numbers | Stripe Documentation",
    "description": "Use the Stripe Dashboard to examine the details of your revenue numbers.",
    "sourceURL": "https://docs.stripe.com/revenue-recognition/reports/audit-numbers"
  }
}