{
  "content": "# Stripe Tax Connector for BigCommerce\n\n## Learn about the Stripe Tax Connector for BigCommerce.\n\nUse the Stripe Tax Connector for BigCommerce to automatically [calculate and\ncollect](https://docs.stripe.com/tax/calculating) sales tax, VAT, and GST. The\nconnector applies the accurate tax rate for all your transactions in your\n[BigCommerce](https://www.bigcommerce.com/) store.\n\nStripe Tax\n[pricing](https://support.stripe.com/questions/understanding-stripe-tax-pricing)\nis usage-based. Users of the Stripe Tax Connector for BigCommerce pay based on\nPAYG Stripe Tax API pricing or the selected subscription-based pricing.\n\n[InstallationInstall the Stripe Tax Connector for\nBigCommerce.](https://docs.stripe.com/connectors/bigcommerce/installation)[ConfigurationConfigure\nthe Stripe Tax Connector for\nBigCommerce.](https://docs.stripe.com/connectors/bigcommerce/configuration)[TroubleshootingTest\nand troubleshoot the features of the Stripe Tax Connector for\nBigCommerce.](https://docs.stripe.com/connectors/bigcommerce/troubleshooting)\n[Contact us](mailto:stripe-tax-bigc-support@stripe.com) if you have additional\nquestions.\n\n## Links\n\n- [calculate and collect](https://docs.stripe.com/tax/calculating)\n- [BigCommerce](https://www.bigcommerce.com/)\n-\n[pricing](https://support.stripe.com/questions/understanding-stripe-tax-pricing)\n- [InstallationInstall the Stripe Tax Connector for\nBigCommerce.](https://docs.stripe.com/connectors/bigcommerce/installation)\n- [ConfigurationConfigure the Stripe Tax Connector for\nBigCommerce.](https://docs.stripe.com/connectors/bigcommerce/configuration)\n- [TroubleshootingTest and troubleshoot the features of the Stripe Tax Connector\nfor\nBigCommerce.](https://docs.stripe.com/connectors/bigcommerce/troubleshooting)",
  "metadata": {
    "title": "Stripe Tax Connector for BigCommerce | Stripe Documentation",
    "description": "Learn about the Stripe Tax Connector for BigCommerce.",
    "sourceURL": "https://docs.stripe.com/connectors/bigcommerce"
  }
}