{
  "content": "# Adds new director verification error codes to the Accounts APIBreaking changes\n\n## What’s new\n\nAdds `verification_missing_directors`, `verification_directors_mismatch`,\n`verification_document_directors_mismatch`, and\n`verification_extraneous_directors` as new error codes in the\n`requirements.errors` array in the Accounts API. To learn more, see [Account\nrequirements\nerrors](https://docs.stripe.com/api/accounts/object#account_object-requirements-errors).\n\n## Impact\n\nAdds four new error codes to the `requirements.errors` array in the Accounts API\nfor director verification issues. These codes provide specific information about\ndirector-related verification problems.\n\n## Upgrade\n\n- [View your current API\nversion](https://docs.stripe.com/upgrades#view-your-api-version-and-the-latest-available-upgrade-in-workbench)\nin Workbench.\n- If you use an SDK, upgrade to the corresponding SDK version for this API\nversion.- If you don’t use an SDK, update your [API\nrequests](https://docs.stripe.com/api/versioning) to include `Stripe-Version:\n2023-08-16`\n- Upgrade the API version used for [webhook\nendpoints](https://docs.stripe.com/webhooks/versioning).\n- [Test your integration](https://docs.stripe.com/testing) against the new\nversion.\n- If you use Connect, [test your Connect\nintegration](https://docs.stripe.com/connect/testing).\n- In Workbench, [perform the\nupgrade](https://docs.stripe.com/upgrades#perform-the-upgrade). You can [roll\nback the version](https://docs.stripe.com/upgrades#roll-back-your-api-version)\nfor 72 hours.\n\nLearn more about [Stripe API upgrades](https://docs.stripe.com/upgrades).\n\n## Links\n\n- [Account requirements\nerrors](https://docs.stripe.com/api/accounts/object#account_object-requirements-errors)\n- [View your current API\nversion](https://docs.stripe.com/upgrades#view-your-api-version-and-the-latest-available-upgrade-in-workbench)\n- [API requests](https://docs.stripe.com/api/versioning)\n- [webhook endpoints](https://docs.stripe.com/webhooks/versioning)\n- [Test your integration](https://docs.stripe.com/testing)\n- [test your Connect integration](https://docs.stripe.com/connect/testing)\n- [perform the upgrade](https://docs.stripe.com/upgrades#perform-the-upgrade)\n- [roll back the\nversion](https://docs.stripe.com/upgrades#roll-back-your-api-version)\n- [Stripe API upgrades](https://docs.stripe.com/upgrades)",
  "metadata": {
    "title": "Adds new director verification error codes to the Accounts API | Stripe Documentation",
    "description": "",
    "sourceURL": "https://docs.stripe.com/changelog/2023-08-16/adds-director-verfication-error-accounts"
  }
}