{
  "content": "# Customize the submit button recurring Payment Links and Checkout Sessions\n\n## What’s new\n\nYou can now [customize the submit\nbutton](https://docs.stripe.com/payments/checkout/customization/behavior#submit-button)\nfor [Checkout Sessions](https://docs.stripe.com/api/checkout/sessions) and\n[Payment Links](https://docs.stripe.com/api/payment-link) with recurring items.\n\nWe added support for the\n[submit_type](https://docs.stripe.com/api/checkout/sessions/create#create_checkout_session-submit_type)\nparameter when you create a Session where the\n[mode](https://docs.stripe.com/api/checkout/sessions/create#create_checkout_session-mode)\nis set to `subscription`. This change also includes support for making updates\nto the `submit_type` on existing Payment Links.\n\n## Impact\n\nUsers can now [customize the behavior of\nCheckout](https://docs.stripe.com/payments/checkout/customization/behavior?payment-ui=embedded-form#submit-button)\nto use `donate` as the text for the submit button for recurring payments.\n\n## Changes\n\nREST APIRubyPythonPHPJavaNodeGo.NETParameterChangeResources or\nendpointssubmit_typeAdded[PaymentLink#update](https://docs.stripe.com/api/payment-link/update)ValueChangeEnumssubscribeAdded[Checkout.Session#create.submit_type](https://docs.stripe.com/api/checkout/sessions/create#create_checkout_session-submit_type)[Checkout.Session.submit_type](https://docs.stripe.com/api/checkout/sessions/object#checkout_session_object-submit_type)[PaymentLink#create.submit_type](https://docs.stripe.com/api/payment-link/create#create_payment_link-submit_type)\n+ 1 more\n## Upgrade\n\n- [View your current API\nversion](https://docs.stripe.com/upgrades#view-your-api-version-and-the-latest-available-upgrade-in-workbench)\nin Workbench.\n- If you use an SDK, upgrade to the corresponding SDK version for this API\nversion.- If you don’t use an SDK, update your [API\nrequests](https://docs.stripe.com/api/versioning) to include `Stripe-Version:\n2024-11-20.acacia`\n- Upgrade the API version used for [webhook\nendpoints](https://docs.stripe.com/webhooks/versioning).\n- [Test your integration](https://docs.stripe.com/testing) against the new\nversion.\n- If you use Connect, [test your Connect\nintegration](https://docs.stripe.com/connect/testing).\n- In Workbench, [perform the\nupgrade](https://docs.stripe.com/upgrades#perform-the-upgrade). You can [roll\nback the version](https://docs.stripe.com/upgrades#roll-back-your-api-version)\nfor 72 hours.\n\nLearn more about [Stripe API upgrades](https://docs.stripe.com/upgrades).\n\n## Related changes\n\n- [Adds support for enabling Adaptive Pricing per Checkout\nSession](https://docs.stripe.com/changelog/acacia/2024-11-20/adaptive-pricing-param)\n- [Adds support for advanced card features on Checkout\nSessions](https://docs.stripe.com/changelog/acacia/2024-11-20/advanced-card-features)\n- [Allows Link card-only integrations to accept non-card payments under Link\ncard brand](https://docs.stripe.com/changelog/acacia/2024-11-20/link-card-brand)\n- [Adds additional beneficiary information for bank transfer\npayments](https://docs.stripe.com/changelog/acacia/2024-11-20/new-bank-transfer-beneficiary-information)\n\n## Links\n\n- [customize the submit\nbutton](https://docs.stripe.com/payments/checkout/customization/behavior#submit-button)\n- [Checkout Sessions](https://docs.stripe.com/api/checkout/sessions)\n- [Payment Links](https://docs.stripe.com/api/payment-link)\n-\n[submit_type](https://docs.stripe.com/api/checkout/sessions/create#create_checkout_session-submit_type)\n-\n[mode](https://docs.stripe.com/api/checkout/sessions/create#create_checkout_session-mode)\n- [customize the behavior of\nCheckout](https://docs.stripe.com/payments/checkout/customization/behavior?payment-ui=embedded-form#submit-button)\n- [PaymentLink#update](https://docs.stripe.com/api/payment-link/update)\n-\n[Checkout.Session.submit_type](https://docs.stripe.com/api/checkout/sessions/object#checkout_session_object-submit_type)\n-\n[PaymentLink#create.submit_type](https://docs.stripe.com/api/payment-link/create#create_payment_link-submit_type)\n-\n[PaymentLink.submit_type](https://docs.stripe.com/api/payment-link/object#payment_link_object-submit_type)\n- [View your current API\nversion](https://docs.stripe.com/upgrades#view-your-api-version-and-the-latest-available-upgrade-in-workbench)\n- [API requests](https://docs.stripe.com/api/versioning)\n- [webhook endpoints](https://docs.stripe.com/webhooks/versioning)\n- [Test your integration](https://docs.stripe.com/testing)\n- [test your Connect integration](https://docs.stripe.com/connect/testing)\n- [perform the upgrade](https://docs.stripe.com/upgrades#perform-the-upgrade)\n- [roll back the\nversion](https://docs.stripe.com/upgrades#roll-back-your-api-version)\n- [Stripe API upgrades](https://docs.stripe.com/upgrades)\n- [Adds support for enabling Adaptive Pricing per Checkout\nSession](https://docs.stripe.com/changelog/acacia/2024-11-20/adaptive-pricing-param)\n- [Adds support for advanced card features on Checkout\nSessions](https://docs.stripe.com/changelog/acacia/2024-11-20/advanced-card-features)\n- [Allows Link card-only integrations to accept non-card payments under Link\ncard brand](https://docs.stripe.com/changelog/acacia/2024-11-20/link-card-brand)\n- [Adds additional beneficiary information for bank transfer\npayments](https://docs.stripe.com/changelog/acacia/2024-11-20/new-bank-transfer-beneficiary-information)",
  "metadata": {
    "title": "Customize the submit button recurring Payment Links and Checkout Sessions | Stripe Documentation",
    "description": "",
    "sourceURL": "https://docs.stripe.com/changelog/acacia/2024-11-20/submit-type-recurring-cpl"
  }
}