{
  "content": "# Set up CapitalPrivate preview\n\n## Determine which integration option to use when you set up Stripe Capital.\n\nStripe Capital is an all-in-one lending solution that allows you to offer access\nto financing directly to your customers. You have a few different integration\noptions for Stripe Capital:\n\n- **No-code integration**: Start providing access to financing to your customers\nin just a few days, with no engineering overhead required, and light marketing\nsupport.\n- **Low-code integration**: Supplement your no-code integration with a series of\nembedded components which work natively with your existing UX.\n- **API integration**: Leverage our API for conversion and UX customization\noptions.\n\nFor most platforms, the no-code integration provides what your customers need\nwith the least overhead. If you’re interested in using the API, contact our team\nat [capital-review@stripe.com](mailto:capital-review@stripe.com) to request\naccess.\n\nThe following table describes the differences between these three integration\noptions.\n\nProgramNo-code integration RecommendedLow-code integrationAPI\nintegrationEstimated integration timeNo engineering time; send the first offer\nas early as tomorrowHours to daysWeeksCapital offer emailsStripe sends\nco-branded offer emailsStripe sends co-branded offer emails or the platform can\nsend offer emailsPlatform can send offer emailsIn-product notificationsN/AUse\nthe Capital [financing\npromotion](https://docs.stripe.com/connect/supported-embedded-components/capital-financing-promotion)\ncomponent to promote new financing offers.Platform can build custom\nnotificationsCapital applicationStripe-hosted co-branded application flowUse the\nCapital [financing\npromotion](https://docs.stripe.com/connect/supported-embedded-components/capital-financing-promotion)\nor [financing\napplication](https://docs.stripe.com/connect/supported-embedded-components/capital-financing-application)\ncomponent to embed the application flow into your website.Stripe-hosted\nco-branded application flow or embedded componentsUnderwriting and pricingStripe\nmanages the entire underwriting process and sets pricingStripe manages the\nentire underwriting process and sets pricingStripe manages the entire\nunderwriting process and sets pricingServicingStripe manages servicing of\ncustomer loansStripe manages servicing of customer loansStripe manages servicing\nof customer loansComplianceStripe conducts compliance review of custom marketing\nassets and periodic program auditsStripe conducts compliance review of custom\nmarketing assets and periodic program auditsStripe conducts compliance review of\ncustom marketing assets and periodic program audits[No-code integrationSet up\nyour Capital program in the\nDashboard](https://docs.stripe.com/capital/no-code-integration)[Low-code\nintegrationIntegrate Capital embedded components directly into your\nwebsite](https://docs.stripe.com/capital/embedded-component-integration)[API\nintegrationIntegrate with our API to build a custom Capital\nprogram](https://docs.stripe.com/capital/api-integration)\n## See also\n\n- [How to market Capital](https://docs.stripe.com/capital/marketing)\n- [Regulatory compliance](https://docs.stripe.com/capital/regulatory-compliance)\n\n## Links\n\n- [financing\npromotion](https://docs.stripe.com/connect/supported-embedded-components/capital-financing-promotion)\n- [financing\napplication](https://docs.stripe.com/connect/supported-embedded-components/capital-financing-application)\n- [No-code integrationSet up your Capital program in the\nDashboard](https://docs.stripe.com/capital/no-code-integration)\n- [Low-code integrationIntegrate Capital embedded components directly into your\nwebsite](https://docs.stripe.com/capital/embedded-component-integration)\n- [API integrationIntegrate with our API to build a custom Capital\nprogram](https://docs.stripe.com/capital/api-integration)\n- [How to market Capital](https://docs.stripe.com/capital/marketing)\n- [Regulatory compliance](https://docs.stripe.com/capital/regulatory-compliance)",
  "metadata": {
    "title": "Set up Capital | Stripe Documentation",
    "description": "Determine which integration option to use when you set up Stripe Capital.",
    "sourceURL": "https://docs.stripe.com/capital/getting-started"
  }
}