{
  "content": "# Stripe Connector for Salesforce BillingDeprecated\n\n## Learn about the Stripe Connector for Salesforce Billing that you can install on top of Salesforce CPQ and Salesforce Billing.\n\n#### Note\n\nFor integrating with Salesforce CRM, Core, and Platform, we recommend using the\n[Stripe Connector for Salesforce\nPlatform](https://docs.stripe.com/connectors/stripe-connector-for-salesforce/overview).\n\nStripe Connector for Salesforce Billing is a managed package that you install on\ntop of Salesforce CPQ and Salesforce Billing. It allows users to process\npayments through the Salesforce Payment Gateway using Stripe payment service to\ncomplete transactions.\n\nStripe exposes four transaction types directly from the Salesforce Billing UI:\n\n- Tokenization—Create a new payment method on an account and set it as the\ndefault.\n- Charge Transaction—Charge a specific amount to an account.\n- Refund Transaction—Refund a specific amount to an account.\n- Bidirectional Data Sync-See related transactions in both Salesforce and Stripe\ndashboards.\n\nIn addition to the UI-based transaction types, Stripe also offers API-based\ntransaction types, which developers can use to create methods that take\nadvantage of the features on the Stripe payment service:\n\n- Void Token—Remove a payment method from an account.\n- Authorize Transaction—Allocate a specific amount to an account pending a\ncharge.\n- Capture Transaction—Complete a charge on an authorized transaction.\n- Void Transaction—Void a charge on an authorized transaction.\n- Get Payment Status—Return the status of a specific charge.\n- Get Refund Status—Return the status of a specific refund.\n\nThe UI-based transaction types (tokenization, charge, refund) are also supported\nthrough the API.\n\nThe Following Payment Methods are supported:\n\n- **Cards**—Support for global and local card networks\n- **ACH**—ACH Direct Debit payments from customers with a US bank account\n\n## Next steps\n\n- [Installation](https://docs.stripe.com/connectors/salesforce-billing/install)\n-\n[Configuration](https://docs.stripe.com/connectors/salesforce-billing/configuration)\n\n## Links\n\n- [Stripe Connector for Salesforce\nPlatform](https://docs.stripe.com/connectors/stripe-connector-for-salesforce/overview)\n- [Installation](https://docs.stripe.com/connectors/salesforce-billing/install)\n-\n[Configuration](https://docs.stripe.com/connectors/salesforce-billing/configuration)",
  "metadata": {
    "title": "Stripe Connector for Salesforce Billing | Stripe Documentation",
    "description": "Learn about the Stripe Connector for Salesforce Billing that you can install on top of Salesforce CPQ and Salesforce Billing.",
    "sourceURL": "https://docs.stripe.com/connectors/salesforce-billing"
  }
}